resotoshell/__init__.py
resotoshell/__main__.py
resotoshell/authorized_client.py
resotoshell/promptsession.py
resotoshell/protected_files.py
resotoshell/shell.py
resotoshell-3.9.0.dist-info/METADATA
resotoshell-3.9.0.dist-info/WHEEL
resotoshell-3.9.0.dist-info/entry_points.txt
resotoshell-3.9.0.dist-info/top_level.txt
resotoshell-3.9.0.dist-info/RECORD
